{
  "claims": [
    {
      "question_id": "q-009",
      "brand_id": "target-brand",
      "claim_text": "示例科技不支持私有化部署。",
      "subject": "示例科技",
      "predicate": "支持私有化部署",
      "value": false,
      "claim_type": "product_capability",
      "verification_status": "incorrect",
      "reference_fact_id": "fact-001",
      "reference_url": "https://example.com/private-deployment",
      "risk_level": "high",
      "confidence": 0.96
    },
    {
      "question_id": "q-005",
      "brand_id": "target-brand",
      "claim_text": "示例科技支持私有化部署。",
      "subject": "示例科技",
      "predicate": "支持私有化部署",
      "value": true,
      "claim_type": "product_capability",
      "verification_status": "correct",
      "reference_fact_id": "fact-001",
      "reference_url": "https://example.com/private-deployment",
      "risk_level": "high",
      "confidence": 0.95
    },
    {
      "question_id": "q-001",
      "brand_id": "target-brand",
      "claim_text": "示例科技适合需要私有化部署的团队。",
      "subject": "示例科技",
      "predicate": "适用场景",
      "value": "私有化团队",
      "claim_type": "positioning",
      "verification_status": "partially_correct",
      "reference_fact_id": null,
      "reference_url": "https://example.com/product",
      "risk_level": "medium",
      "confidence": 0.7
    },
    {
      "question_id": "q-004",
      "brand_id": "target-brand",
      "claim_text": "品类定义性陈述，无品牌具体能力断言。",
      "subject": "品类",
      "predicate": "定义",
      "value": null,
      "claim_type": "category",
      "verification_status": "unverifiable",
      "reference_fact_id": null,
      "reference_url": null,
      "risk_level": "low",
      "confidence": 0.5
    }
  ]
}